vertexdata/__init__.py
vertexdata/__main__.py
vertexdata/cli.py
vertexdata/main.py
vertexdata/VertexParser.py
vertexdata-1.0.1.dist-info/entry_points.txt
vertexdata-1.0.1.dist-info/LICENSE
vertexdata-1.0.1.dist-info/METADATA
vertexdata-1.0.1.dist-info/WHEEL
vertexdata-1.0.1.dist-info/RECORD
