Metadata-Version: 2.3
Name: vertexdata
Version: 1.0.1
Summary: For parsing obj files to be suitable to feed to a vertex buffer.
License: LICENSE
Author: alternyxx
Author-email: alternyxx@gmail.com
Maintainer: alternyxx
Maintainer-email: alternyxx@gmail.com
Requires-Python: >=3.10
Classifier: License :: Other/Proprietary License
Classifier: Programming Language :: Python :: 3
Classifier: Programming Language :: Python :: 3.10
Classifier: Programming Language :: Python :: 3.11
Classifier: Programming Language :: Python :: 3.12
Classifier: Programming Language :: Python :: 3.13
Project-URL: Repository, https://github.com/alternyxx/VertexData/
